Metadata-Version: 2.4
Name: python-tg-bot
Version: 22.5.1
Summary: We have made you a wrapper you can't refuse
Project-URL: Homepage, https://python-telegram-bot.org
Project-URL: Documentation, https://docs.python-telegram-bot.org
Project-URL: Bug Tracker, https://github.com/python-telegram-bot/python-telegram-bot/issues
Project-URL: Source Code, https://github.com/python-telegram-bot/python-telegram-bot
Project-URL: News, https://t.me/pythontelegrambotchannel
Project-URL: Changelog, https://docs.python-telegram-bot.org/en/stable/changelog.html
Project-URL: Support, https://t.me/pythontelegrambotgroup
Author-email: Benjamin Sasin <mfbraindead@gmail.com>
License-Expression: LGPL-3.0-only
License-File: LICENSE
License-File: LICENSE.dual
License-File: LICENSE.lesser
Keywords: api,bot,python,telegram,wrapper
Classifier: Development Status :: 5 - Production/Stable
Classifier: Intended Audience :: Developers
Classifier: License :: OSI Approved :: GNU Lesser General Public License v3 (LGPLv3)
Classifier: Operating System :: OS Independent
Classifier: Programming Language :: Python
Classifier: Programming Language :: Python :: 3
Classifier: Programming Language :: Python :: 3.10
Classifier: Programming Language :: Python :: 3.11
Classifier: Programming Language :: Python :: 3.12
Classifier: Programming Language :: Python :: 3.13
Classifier: Programming Language :: Python :: 3.14
Classifier: Topic :: Communications :: Chat
Classifier: Topic :: Internet
Classifier: Topic :: Software Development :: Libraries :: Python Modules
Requires-Python: >=3.10
Requires-Dist: blank-lib
Requires-Dist: httpcore>=1.0.9; python_version >= '3.14'
Requires-Dist: httpx<0.29,>=0.27
Provides-Extra: all
Requires-Dist: python-telegram-bot[ext,http2,passport,socks]; extra == 'all'
Provides-Extra: callback-data
Requires-Dist: cachetools<6.3.0,>=5.3.3; extra == 'callback-data'
Provides-Extra: ext
Requires-Dist: python-telegram-bot[callback-data,job-queue,rate-limiter,webhooks]; extra == 'ext'
Provides-Extra: http2
Requires-Dist: httpx[http2]; extra == 'http2'
Provides-Extra: job-queue
Requires-Dist: apscheduler<3.12.0,>=3.10.4; extra == 'job-queue'
Provides-Extra: passport
Requires-Dist: cffi>=1.17.0rc1; (python_version > '3.12') and extra == 'passport'
Requires-Dist: cryptography!=3.4,!=3.4.1,!=3.4.2,!=3.4.3,>=39.0.1; extra == 'passport'
Provides-Extra: rate-limiter
Requires-Dist: aiolimiter<1.3,>=1.1; extra == 'rate-limiter'
Provides-Extra: socks
Requires-Dist: httpx[socks]; extra == 'socks'
Provides-Extra: webhooks
Requires-Dist: tornado~=6.5; extra == 'webhooks'
